servicing-0.0.12.dist-info/METADATA
servicing-0.0.12.dist-info/WHEEL
servicing/__init__.py
servicing/__init__.pyi
servicing/py.typed
servicing/servicing.cpython-311-darwin.so
servicing-0.0.12.dist-info/RECORD
